wom/__init__.py
wom/__main__.py
wom/client.py
wom/constants.py
wom/enums.py
wom/errors.py
wom/models/__init__.py
wom/models/base.py
wom/models/competitions/__init__.py
wom/models/competitions/enums.py
wom/models/competitions/models.py
wom/models/deltas/__init__.py
wom/models/deltas/models.py
wom/models/groups/__init__.py
wom/models/groups/enums.py
wom/models/groups/models.py
wom/models/http.py
wom/models/names/__init__.py
wom/models/names/enums.py
wom/models/names/models.py
wom/models/players/__init__.py
wom/models/players/enums.py
wom/models/players/models.py
wom/models/records/__init__.py
wom/models/records/models.py
wom/py.typed
wom/result.py
wom/routes.py
wom/serializer.py
wom/services/__init__.py
wom/services/base.py
wom/services/competitions.py
wom/services/deltas.py
wom/services/efficiency.py
wom/services/groups.py
wom/services/http.py
wom/services/names.py
wom/services/players.py
wom/services/records.py
wom_py-2.0.6.dist-info/METADATA
wom_py-2.0.6.dist-info/WHEEL
wom_py-2.0.6.dist-info/entry_points.txt
wom_py-2.0.6.dist-info/licenses/LICENSE
wom_py-2.0.6.dist-info/RECORD
