Metadata-Version: 2.4
Name: wom.py
Version: 2.0.6
Summary: An asynchronous wrapper for the Wise Old Man API.
License: MIT
License-File: LICENSE
Author: Jonxslays
Requires-Python: >=3.9
Classifier: Development Status :: 5 - Production/Stable
Classifier: Framework :: AsyncIO
Classifier: Intended Audience :: Developers
Classifier: License :: OSI Approved :: MIT License
Classifier: Operating System :: OS Independent
Classifier: Programming Language :: Python :: 3
Classifier: Programming Language :: Python :: 3.9
Classifier: Programming Language :: Python :: 3.10
Classifier: Programming Language :: Python :: 3.11
Classifier: Programming Language :: Python :: 3.12
Classifier: Programming Language :: Python :: 3.13
Classifier: Programming Language :: Python :: 3.14
Classifier: Programming Language :: Python :: 3 :: Only
Classifier: Topic :: Software Development :: Libraries
Classifier: Topic :: Software Development :: Libraries :: Python Modules
Classifier: Typing :: Typed
Requires-Dist: aiohttp (>3.8.1)
Requires-Dist: msgspec (>=0.19.0)
Project-URL: Documentation, https://jonxslays.github.io/wom.py
Project-URL: Homepage, https://github.com/Jonxslays/wom.py
Project-URL: Repository, https://github.com/Jonxslays/wom.py
